{"cameraMode":{"drawMode":0,"name":"Shaded","section":"Shading Mode"},"sceneLighting":true,"audioPlay":false,"sceneViewState":{"showFog":true,"showMaterialUpdate":false,"showSkybox":true,"showFlares":true,"showImageEffects":true,"showParticleSystems":true},"in2DMode":false,"pivot":{"x":35.271644592285159,"y":-7.8380446434021,"z":37.76666259765625},"rotation":{"x":0.1748685985803604,"y":0.2775970995426178,"z":-0.05148432403802872,"w":0.9432838559150696},"size":71.01525115966797,"orthographic":false}